cloud_resource_matcher/__init__.py
cloud_resource_matcher/modules/__init__.py
cloud_resource_matcher/modules/base/__init__.py
cloud_resource_matcher/modules/base/data.py
cloud_resource_matcher/modules/base/mip_construction.py
cloud_resource_matcher/modules/base/solution_extraction.py
cloud_resource_matcher/modules/base/validation.py
cloud_resource_matcher/modules/multi_cloud/__init__.py
cloud_resource_matcher/modules/multi_cloud/data.py
cloud_resource_matcher/modules/multi_cloud/mip_construction.py
cloud_resource_matcher/modules/multi_cloud/validation.py
cloud_resource_matcher/modules/network/__init__.py
cloud_resource_matcher/modules/network/data.py
cloud_resource_matcher/modules/network/mip_construction.py
cloud_resource_matcher/modules/network/pre_processing.py
cloud_resource_matcher/modules/network/validation.py
cloud_resource_matcher/modules/performance/__init__.py
cloud_resource_matcher/modules/performance/data.py
cloud_resource_matcher/modules/performance/mip_construction.py
cloud_resource_matcher/modules/performance/pre_processing.py
cloud_resource_matcher/modules/performance/validation.py
cloud_resource_matcher/modules/service_limits/__init__.py
cloud_resource_matcher/modules/service_limits/data.py
cloud_resource_matcher/modules/service_limits/mip_construction.py
cloud_resource_matcher/modules/service_limits/validation.py
cloud_resource_matcher/py.typed
cloud_resource_matcher/solver.py
cloud_resource_matcher-0.2.0.dist-info/METADATA
cloud_resource_matcher-0.2.0.dist-info/entry_points.txt
cloud_resource_matcher-0.2.0.dist-info/LICENSE
cloud_resource_matcher-0.2.0.dist-info/WHEEL
cloud_resource_matcher-0.2.0.dist-info/RECORD
