Metadata-Version: 2.1
Name: cloud-resource-matcher
Version: 0.2.0
Summary: A framework to optimize costs of cloud computing deployments.
Home-page: https://github.com/TimJentzsch/cloud_resource_matcher
License: MIT
Author: Tim Jentzsch
Author-email: cloud_resource_matcher.projects@timjen.net
Requires-Python: >=3.11,<4.0
Classifier: License :: OSI Approved :: MIT License
Classifier: Programming Language :: Python :: 3
Classifier: Programming Language :: Python :: 3.11
Requires-Dist: optiframe (>=0.5.0,<0.6.0)
Requires-Dist: pulp (>=2.7.0,<3.0.0)
Project-URL: Repository, https://github.com/TimJentzsch/cloud_resource_matcher
